boids_utils/__init__.py
boids_utils/config.py
boids_utils/elastic/__init__.py
boids_utils/elastic/exceptions.py
boids_utils/elastic/index.py
boids_utils/elastic/manager.py
boids_utils/logging.py
boids_utils/openapi.py
boids_utils/pubsub/__init__.py
boids_utils/pubsub/exceptions.py
boids_utils/pubsub/manager.py
boids_utils/pubsub/topic.py
boids_utils/template.py
boids_utils/test/__init__.py
boids_utils/test/containers/__init__.py
boids_utils/test/containers/elasticsearch.py
boids_utils/test/containers/nats.py
boids_utils-1.1.5.dist-info/LICENSE
boids_utils-1.1.5.dist-info/METADATA
boids_utils-1.1.5.dist-info/WHEEL
boids_utils-1.1.5.dist-info/RECORD
