Metadata-Version: 2.1
Name: boids-utils
Version: 1.1.5
Summary: Utilities common to the Boids application
Author: Kerry Johnson
Author-email: kerry.t.johnson@gmail.com
Requires-Python: >=3.10,<4.0
Classifier: Programming Language :: Python :: 3
Classifier: Programming Language :: Python :: 3.10
Classifier: Programming Language :: Python :: 3.11
Requires-Dist: PyYAML (>=6.0,<7.0)
Requires-Dist: aiohttp (==3.9.0)
Requires-Dist: aiohttp-jinja2 (>=1.5.1,<2.0.0)
Requires-Dist: backoff (>=2.2.1,<3.0.0)
Requires-Dist: boids-api (==1.0.3)
Requires-Dist: colorlog (>=6.7.0,<7.0.0)
Requires-Dist: connexion (>=2.14.2,<3.0.0)
Requires-Dist: elasticsearch (>=8.9.0,<9.0.0)
Requires-Dist: jinja2 (>=3.1.2,<4.0.0)
Requires-Dist: mergedeep (>=1.3.4,<2.0.0)
Requires-Dist: nats-py (>=2.4.0,<3.0.0)
Requires-Dist: python-dateutil (>=2.8.2,<3.0.0)
Requires-Dist: requests (>=2.28.2,<3.0.0)
Requires-Dist: rich (>=13.3.1,<14.0.0)
Requires-Dist: whistle (>=1.0.1,<2.0.0)
Requires-Dist: yarl (>=1.9.2,<2.0.0)
